main.py
src/__init__.py
src/embeddings.py
src/memory_store.py
src/models.py
src/security.py
vector_memory_mcp-1.0.4.dist-info/licenses/LICENSE
vector_memory_mcp-1.0.4.dist-info/METADATA
vector_memory_mcp-1.0.4.dist-info/WHEEL
vector_memory_mcp-1.0.4.dist-info/entry_points.txt
vector_memory_mcp-1.0.4.dist-info/top_level.txt
vector_memory_mcp-1.0.4.dist-info/RECORD
