Metadata-Version: 2.4
Name: vector-memory-mcp
Version: 1.0.4
Summary: A secure, vector-based memory server for Claude Desktop using sqlite-vec and sentence-transformers
Author-email: Xsaven <xsaven@gmail.com>
License-Expression: MIT
Project-URL: Homepage, https://github.com/xsaven/vector-memory-mcp
Project-URL: Repository, https://github.com/xsaven/vector-memory-mcp
Project-URL: Issues, https://github.com/xsaven/vector-memory-mcp/issues
Keywords: mcp,model-context-protocol,vector-search,sqlite,embeddings,semantic-search,claude,ai-memory
Classifier: Development Status :: 4 - Beta
Classifier: Intended Audience :: Developers
Classifier: Programming Language :: Python :: 3
Classifier: Programming Language :: Python :: 3.10
Classifier: Programming Language :: Python :: 3.11
Classifier: Programming Language :: Python :: 3.12
Classifier: Topic :: Software Development :: Libraries :: Python Modules
Classifier: Topic :: Scientific/Engineering :: Artificial Intelligence
Requires-Python: >=3.10
License-File: LICENSE
Requires-Dist: mcp>=0.3.0
Requires-Dist: sqlite-vec>=0.1.6
Requires-Dist: sentence-transformers>=2.2.2
Requires-Dist: requests>=2.28.0
Dynamic: license-file
